SignLanguageRecognition/__init__.py
SignLanguageRecognition/action.h5
SignLanguageRecognition/signLanguageRecognizer.py
SignLanguageRecognition-0.0.20.1.dist-info/LICENSE
SignLanguageRecognition-0.0.20.1.dist-info/METADATA
SignLanguageRecognition-0.0.20.1.dist-info/WHEEL
SignLanguageRecognition-0.0.20.1.dist-info/top_level.txt
SignLanguageRecognition-0.0.20.1.dist-info/RECORD
